py3status_amdfan/__init__.py
py3status_amdfan/fan_monitor.py
py3status_amdfan-0.1.18.dist-info/LICENSE
py3status_amdfan-0.1.18.dist-info/METADATA
py3status_amdfan-0.1.18.dist-info/WHEEL
py3status_amdfan-0.1.18.dist-info/entry_points.txt
py3status_amdfan-0.1.18.dist-info/RECORD
