Metadata-Version: 2.3
Name: py3status-amdfan
Version: 0.1.18
Summary: py3status monitor show amdgpu fan speeds and temp
License: MIT
Keywords: amdgpu,monitor,fan,i3,py3status
Author: mcgillij
Author-email: mcgillivray.jason@gmail.com
Requires-Python: >=3.11,<4.0
Classifier: Environment :: X11 Applications
Classifier: Intended Audience :: End Users/Desktop
Classifier: License :: OSI Approved :: MIT License
Classifier: Operating System :: POSIX :: Linux
Classifier: Programming Language :: Python :: 3
Classifier: Programming Language :: Python :: 3.11
Classifier: Programming Language :: Python :: 3.12
Classifier: Programming Language :: Python :: 3.13
Classifier: Topic :: Desktop Environment :: Window Managers
Classifier: Topic :: System :: Hardware
Classifier: Topic :: System :: Monitoring
Requires-Dist: amdfan (>=0.2.5,<0.3.0)
Requires-Dist: py3status (>=3.62,<4.0)
Project-URL: Documentation, https://github.com/mcgillij/py3status-amdfan
Project-URL: Homepage, https://github.com/mcgillij/py3status-amdfan
Project-URL: Repository, https://github.com/mcgillij/py3status-amdfan
